syrtis_python_client-0.0.6.dist-info/METADATA
syrtis_python_client-0.0.6.dist-info/WHEEL
syrtis_python_client-0.0.6.dist-info/entry_points.txt
syrtis_python_client/__init__.py
syrtis_python_client/py.typed
syrtis_python_client-0.0.6.dist-info/RECORD
